chenhuiming/__init__.py
chenhuiming/pyarmor_runtime.pyd
chenhuiming/test.py
chenhuiming/pyarmor_runtime_000000/__init__.py
chenhuiming/pyarmor_runtime_000000/pyarmor_runtime.pyd
chenhuiming-0.2.3.dist-info/LICENSE
chenhuiming-0.2.3.dist-info/METADATA
chenhuiming-0.2.3.dist-info/WHEEL
chenhuiming-0.2.3.dist-info/license.lic
chenhuiming-0.2.3.dist-info/top_level.txt
chenhuiming-0.2.3.dist-info/RECORD
