Metadata-Version: 2.1
Name: chenhuiming
Version: 0.2.3
Summary: a private package
Home-page: UNKNOWN
Author: chenhuiming
Author-email: 1250266701@qq.com
License: MIT
Platform: UNKNOWN
Classifier: Development Status :: 3 - Alpha
Classifier: Intended Audience :: Developers
Classifier: Topic :: Software Development :: Build Tools
Classifier: License :: OSI Approved :: MIT License
Classifier: Programming Language :: Python :: 3
Classifier: Programming Language :: Python :: 3.6
Classifier: Programming Language :: Python :: 3.7
Classifier: Programming Language :: Python :: 3.8
Classifier: Programming Language :: Python :: 3.9
Classifier: Programming Language :: Python :: 3.10
Requires-Python: >=3
Requires-Dist: numpy (>=1.18.1)
Requires-Dist: librosa (==0.9.2)
Requires-Dist: soundfile
Requires-Dist: scikit-learn
Requires-Dist: pyarmor
